LICENSE
MANIFEST.in
README.md
setup.py
docs/2d.png
docs/3d.png
docs/forest.png
docs/office.png
docs/office_3d.png
docs/logo/logo.png
src/external/DecompUtil/include/decomp_basis/data_type.h
src/external/DecompUtil/include/decomp_basis/data_utils.h
src/external/DecompUtil/include/decomp_geometry/ellipsoid.h
src/external/DecompUtil/include/decomp_geometry/geometric_utils.h
src/external/DecompUtil/include/decomp_geometry/polyhedron.h
src/external/DecompUtil/include/decomp_util/decomp_base.h
src/external/DecompUtil/include/decomp_util/ellipsoid_decomp.h
src/external/DecompUtil/include/decomp_util/iterative_decomp.h
src/external/DecompUtil/include/decomp_util/line_segment.h
src/external/DecompUtil/include/decomp_util/seed_decomp.h
src/external/pybind11/include/pybind11/attr.h
src/external/pybind11/include/pybind11/buffer_info.h
src/external/pybind11/include/pybind11/cast.h
src/external/pybind11/include/pybind11/chrono.h
src/external/pybind11/include/pybind11/common.h
src/external/pybind11/include/pybind11/complex.h
src/external/pybind11/include/pybind11/eigen.h
src/external/pybind11/include/pybind11/embed.h
src/external/pybind11/include/pybind11/eval.h
src/external/pybind11/include/pybind11/functional.h
src/external/pybind11/include/pybind11/gil.h
src/external/pybind11/include/pybind11/iostream.h
src/external/pybind11/include/pybind11/numpy.h
src/external/pybind11/include/pybind11/operators.h
src/external/pybind11/include/pybind11/options.h
src/external/pybind11/include/pybind11/pybind11.h
src/external/pybind11/include/pybind11/pytypes.h
src/external/pybind11/include/pybind11/stl.h
src/external/pybind11/include/pybind11/stl_bind.h
src/external/pybind11/include/pybind11/type_caster_pyobject_ptr.h
src/external/pybind11/include/pybind11/typing.h
src/external/pybind11/include/pybind11/detail/class.h
src/external/pybind11/include/pybind11/detail/common.h
src/external/pybind11/include/pybind11/detail/descr.h
src/external/pybind11/include/pybind11/detail/init.h
src/pydecomp.egg-info/PKG-INFO
src/pydecomp.egg-info/SOURCES.txt
src/pydecomp.egg-info/dependency_links.txt
src/pydecomp.egg-info/requires.txt
src/pydecomp.egg-info/top_level.txt
