Metadata-Version: 2.1
Name: pydecomp
Version: 0.0.4
Summary: A Python package for decomposing obstacle free spaces into convex polygons
Home-page: https://github.com/jonarriza96/pydecomp
Author: Jon Arrizabalaga
Author-email: arrijon96@gmail.com
License: MIT
Classifier: License :: OSI Approved :: MIT License
Classifier: Programming Language :: Python :: 3.9
Classifier: Operating System :: OS Independent
License-File: LICENSE
